openctm/version.py
openctm/io.py
openctm/__init__.py
openctm/openctm.py
openctm/libs/libopenctm.dylib
openctm/libs/openctm.h
openctm/libs/openctm.o
openctm/libs/openctm.rc
openctm/libs/openctm.c
python_openctm-1.0.12.dist-info/RECORD
python_openctm-1.0.12.dist-info/LICENSE
python_openctm-1.0.12.dist-info/WHEEL
python_openctm-1.0.12.dist-info/top_level.txt
python_openctm-1.0.12.dist-info/METADATA
