Metadata-Version: 2.1
Name: python-openctm
Version: 1.0.12
Summary: Python Interface for the OpenCTM File Format
Home-page: https://github.com/lejafar/python-openctm
Author: Rafael Hautekiet
Author-email: rafaelhautekiet@gmail.com
License: zlib License
Platform: UNKNOWN
Classifier: Programming Language :: Python :: 3.5
Classifier: Programming Language :: Python :: 3.6
Classifier: Programming Language :: Python :: 3.7
Classifier: Programming Language :: Python :: 3.8
Classifier: Natural Language :: English
Classifier: Topic :: Scientific/Engineering
Classifier: License :: OSI Approved :: zlib/libpng License
Classifier: Operating System :: OS Independent
